conway_polynomials/CPimport.txt.xz
conway_polynomials/__init__.py
conway_polynomials-0.10.dist-info/COPYING
conway_polynomials-0.10.dist-info/LICENSE
conway_polynomials-0.10.dist-info/METADATA
conway_polynomials-0.10.dist-info/WHEEL
conway_polynomials-0.10.dist-info/top_level.txt
conway_polynomials-0.10.dist-info/RECORD
