Metadata-Version: 2.1
Name: conway-polynomials
Version: 0.10
Summary: Python interface to Frank Lübeck's Conway polynomial database
License: conway-polynomials - a python interface to Frank Lübeck's Conway polynomial database
Project-URL: Homepage, https://github.com/sagemath/conway-polynomials
Project-URL: Documentation, https://github.com/sagemath/conway-polynomials/blob/master/README.rst
Project-URL: Repository, https://github.com/sagemath/conway-polynomials.git
Project-URL: Issues, https://github.com/sagemath/conway-polynomials/issues
Project-URL: Changelog, https://github.com/sagemath/conway-polynomials/raw/master/NEWS
Keywords: mathematics,algebra,Conway polynomials
Classifier: Development Status :: 5 - Production/Stable
Classifier: License :: OSI Approved :: GNU General Public License v3 or later (GPLv3+)
Classifier: Programming Language :: Python :: 3
Classifier: Topic :: Scientific/Engineering :: Mathematics
Classifier: Topic :: Software Development :: Libraries :: Python Modules
Requires-Python: >=3.9
License-File: LICENSE
License-File: COPYING
